visibility_local/__init__.py
visibility_local/visibilities_local.py
visibility_local-0.0.4.dist-info/METADATA
visibility_local-0.0.4.dist-info/WHEEL
visibility_local-0.0.4.dist-info/top_level.txt
visibility_local-0.0.4.dist-info/RECORD
